{
  "video_id": "SWatAxngTTM",
  "year": 2025,
  "date": null,
  "featured_team": "Auburn",
  "target_fanbase": "Florida",
  "home_team": null,
  "away_team": null,
  "final_score": null,
  "video_location_place": "University of Florida campus",
  "video_location_city_state": "Gainesville, Florida",
  "game_or_event_label": "Final Four",
  "rivalry": null,
  "sport": "college basketball",
  "confidence": "high",
  "evidence": "Title and description explicitly state 'Auburn Fan Trolls Florida! (Final Four)' and the uploader was at the University of Florida campus in Gainesville.",
  "needs_review": false,
  "notes": "The video label 'Final Four' refers to the NCAA tournament, which is college basketball."
}